examples/writing_dense_rgb.py
examples/config.py
examples/query_condition_sparse.py
examples/object.py
examples/fragment_info.py
examples/writing_dense_multiple.py
examples/quickstart_dense.py
examples/quickstart_dimension_labels_sparse.py
examples/multi_attribute.py
examples/reading_dense_layouts.py
examples/in_memory_vfs.py
examples/profile.py
examples/query_condition_string.py
examples/incomplete_iteration.py
examples/variable_length.py
examples/quickstart_sparse.py
examples/multirange_indexing.py
examples/using_tiledb_stats.py
examples/query_condition_datetime.py
examples/writing_sparse_multiple.py
examples/string_dimension_labels.py
examples/quickstart_dimension_labels.py
examples/time_traveling.py
examples/vfs.py
examples/query_condition_dense.py
examples/fragments_consolidation.py
examples/reading_sparse_layouts.py
examples/errors.py
examples/parallel_csv_ingestion.py
examples/string_float_int_dimensions.py
examples/writing_dense_padding.py
tiledb/main.cc
tiledb/aggregation.py
tiledb/attribute.py
tiledb/CMakeLists.txt
tiledb/_generated_version.py
tiledb/metadata.py
tiledb/py_arrowio
tiledb/enumeration.py
tiledb/query.py
tiledb/domain.py
tiledb/object.py
tiledb/serialization.cc
tiledb/array_schema.py
tiledb/fragment.cc
tiledb/query_condition.py
tiledb/dataframe_.py
tiledb/subarray.py
tiledb/profile.py
tiledb/data_order.py
tiledb/sparse_array.py
tiledb/highlevel.py
tiledb/__init__.py
tiledb/npbuffer.cc
tiledb/multirange_indexing.py
tiledb/py_arrow_io_impl.h
tiledb/schema_evolution.py
tiledb/consolidation_plan.py
tiledb/parquet_.py
tiledb/debug.cc
tiledb/main.cpython-314-darwin.so
tiledb/current_domain.py
tiledb/version_helper.py
tiledb/dense_array.py
tiledb/datatypes.py
tiledb/util.cc
tiledb/fragment.py
tiledb/vfs.py
tiledb/query_condition.cc
tiledb/schema_evolution.cc
tiledb/ndrectangle.py
tiledb/stats.py
tiledb/dimension_label_schema.py
tiledb/util.h
tiledb/group.py
tiledb/core.cc
tiledb-0.35.2.dist-info/RECORD
tiledb-0.35.2.dist-info/WHEEL
tiledb-0.35.2.dist-info/METADATA
tiledb-0.35.2.dist-info/licenses/LICENSE
tiledb-0.35.2.dist-info/licenses/external/LICENSE-tsl_robin_map.txt
tiledb-0.35.2.dist-info/licenses/external/LICENSE-string_view.txt
