Metadata-Version: 2.2
Name: tiledb
Version: 0.35.2
Summary: Pythonic interface to the TileDB array storage manager
Author-Email: "TileDB, Inc." <help@tiledb.io>
Maintainer-Email: "TileDB, Inc." <help@tiledb.io>
License: MIT
Classifier: Development Status :: 4 - Beta
Classifier: Intended Audience :: Developers
Classifier: Intended Audience :: Information Technology
Classifier: Intended Audience :: Science/Research
Classifier: License :: OSI Approved :: MIT License
Classifier: Programming Language :: Python
Classifier: Topic :: Software Development :: Libraries :: Python Modules
Classifier: Operating System :: Unix
Classifier: Operating System :: POSIX :: Linux
Classifier: Operating System :: MacOS :: MacOS X
Classifier: Programming Language :: Python :: 3
Classifier: Programming Language :: Python :: 3.9
Classifier: Programming Language :: Python :: 3.10
Classifier: Programming Language :: Python :: 3.11
Classifier: Programming Language :: Python :: 3.12
Classifier: Programming Language :: Python :: 3.13
Classifier: Programming Language :: Python :: 3.14
Project-URL: homepage, https://github.com/TileDB-Inc/TileDB-Py
Requires-Python: >=3.9
Requires-Dist: numpy>=1.25
Requires-Dist: packaging
Provides-Extra: doc
Requires-Dist: jinja2==3.1.5; extra == "doc"
Requires-Dist: sphinx-rtd-theme==3.0.2; extra == "doc"
Requires-Dist: Sphinx==8.1.3; extra == "doc"
Requires-Dist: nbsphinx==0.9.6; extra == "doc"
Requires-Dist: breathe; extra == "doc"
Provides-Extra: test
Requires-Dist: pytest; extra == "test"
Requires-Dist: pytest-rerunfailures; extra == "test"
Requires-Dist: hypothesis; extra == "test"
Requires-Dist: psutil; extra == "test"
Requires-Dist: pyarrow; extra == "test"
Requires-Dist: pandas; extra == "test"
Requires-Dist: dask[distributed]; extra == "test"
